{
  "$schema": "https://ui.shadcn.com/schema/registry-item.json",
  "name": "metal-button-bronze",
  "type": "registry:ui",
  "title": "Metal Button Bronze",
  "author": "Lakshay Bhushan",
  "description": "A shadcn/ui based button but it's made of bronze metal",
  "registryDependencies": [
    "https://button.lakshb.dev/r/metal-button.json"
  ],
  "files": [
    {
      "path": "registry/example/metal-button-bronze.tsx",
      "content": "import { MetalButton } from \"@/components/metal-button\";\n\nexport function MetalButtonBronze() {\n  return (\n    <div>\n      <MetalButton variant=\"bronze\">Bronze</MetalButton>\n    </div>\n  );\n}\n",
      "type": "registry:ui",
      "target": "components/metal-button-bronze.tsx"
    }
  ]
}